ml_mearec/__init__.py
ml_mearec/ml_mearec.py
ml_mearec/ml_mearec.py.mp
ml_mearec/MEArec/__init__.py
ml_mearec/MEArec/gen_recordings.py
ml_mearec/MEArec/gen_spiketrains.py
ml_mearec/MEArec/tools.py
ml_mearec-0.1.7.dist-info/METADATA
ml_mearec-0.1.7.dist-info/RECORD
ml_mearec-0.1.7.dist-info/WHEEL
ml_mearec-0.1.7.dist-info/top_level.txt
