Metadata-Version: 2.1
Name: ml-mearec
Version: 0.1.7
Summary: MountainLab wrapper for MEArec
Home-page: https://github.com/magland/ml_mearec
Author: Jeremy Magland
Author-email: 
License: UNKNOWN
Platform: UNKNOWN
Classifier: Programming Language :: Python :: 3
Classifier: License :: OSI Approved :: Apache Software License
Classifier: Operating System :: OS Independent
Requires-Dist: MEAutility
Requires-Dist: h5py
Requires-Dist: numpy
Requires-Dist: click
Requires-Dist: neo
Requires-Dist: elephant
Requires-Dist: matplotlib
Requires-Dist: scipy
Requires-Dist: quantities
Requires-Dist: pyyaml
Requires-Dist: numpy
Requires-Dist: mlprocessors
Requires-Dist: mountainlab-pytools
Requires-Dist: prompt-toolkit
